soyclustering/__init__.py
soyclustering/_keyword.py
soyclustering/_kmeans.py
soyclustering/_postprocess.py
soyclustering/_utils.py
soyclustering/_visualize.py
soyclustering-0.2.0.dist-info/LICENSE
soyclustering-0.2.0.dist-info/METADATA
soyclustering-0.2.0.dist-info/WHEEL
soyclustering-0.2.0.dist-info/top_level.txt
soyclustering-0.2.0.dist-info/RECORD
