Metadata-Version: 2.1
Name: soyclustering
Version: 0.2.0
Summary: Python library for document clustering
Home-page: https://github.com/lovit/clustering4docs
Author: Lovit
Author-email: soy.lovit@gmail.com
License: UNKNOWN
Keywords: document clustering,clustering labeling
Platform: UNKNOWN
Requires-Dist: numpy (>=1.1)
